TwineW/TwineW.py
TwineW/__init__.py
twinew-1.0.0.dist-info/licenses/LICENSE
twinew-1.0.0.dist-info/METADATA
twinew-1.0.0.dist-info/WHEEL
twinew-1.0.0.dist-info/top_level.txt
twinew-1.0.0.dist-info/RECORD
