Metadata-Version: 2.4
Name: twinew
Version: 1.0.0
Summary: Library allowing for endurance macro software to be configured and created.
Author: WilsonSTW
Classifier: Programming Language :: Python :: 3
Classifier: License :: OSI Approved :: MIT License
Classifier: Operating System :: OS Independent
Requires-Python: >=3.8
License-File: LICENSE
Requires-Dist: pyautogui
Dynamic: license-file
